xml_boiler-0.9.15.data/scripts/boiler
xmlboiler/__init__.py
xmlboiler/command_line/__init__.py
xmlboiler/command_line/command.py
xmlboiler/command_line/common.py
xmlboiler/command_line/modifiers.py
xmlboiler/command_line/pipe.py
xmlboiler/core/__init__.py
xmlboiler/core/asset_downloaders.py
xmlboiler/core/data.py
xmlboiler/core/execution_context.py
xmlboiler/core/execution_context_builders.py
xmlboiler/core/options.py
xmlboiler/core/urls.py
xmlboiler/core/alg/__init__.py
xmlboiler/core/alg/auto_transform.py
xmlboiler/core/alg/common.py
xmlboiler/core/alg/download.py
xmlboiler/core/alg/next_script1.py
xmlboiler/core/alg/next_script2.py
xmlboiler/core/alg/next_script_base.py
xmlboiler/core/alg/path.py
xmlboiler/core/alg/script_subcommand.py
xmlboiler/core/alg/state.py
xmlboiler/core/alg/transform_subcommand.py
xmlboiler/core/data/interpreters.ttl
xmlboiler/core/data/mynolocal.net
xmlboiler/core/data/subclasses.ttl
xmlboiler/core/data/assets/http%3A%2F%2Fportonvictor.org%2Fns%2FEMM
xmlboiler/core/data/assets/http%3A%2F%2Fportonvictor.org%2Fns%2FEMM%2Fsections
xmlboiler/core/data/assets/http%3A%2F%2Fportonvictor.org%2Fns%2FEMM%2Ftoc
xmlboiler/core/data/assets/http%3A%2F%2Fportonvictor.org%2Fns%2Fbase
xmlboiler/core/data/assets/http%3A%2F%2Fportonvictor.org%2Fns%2Fcomment
xmlboiler/core/data/assets/http%3A%2F%2Fportonvictor.org%2Fns%2Fhtml
xmlboiler/core/data/assets/http%3A%2F%2Fportonvictor.org%2Fns%2Fsyntax
xmlboiler/core/data/assets/http%3A%2F%2Fwww.w3.org%2F2001%2FXInclude
xmlboiler/core/data/scripts/comment.xslt
xmlboiler/core/data/scripts/copy.xslt
xmlboiler/core/data/scripts/nsclean.xslt
xmlboiler/core/data/scripts/section.xslt
xmlboiler/core/data/scripts/emm/emm-to-xhtml.xslt
xmlboiler/core/graph/__init__.py
xmlboiler/core/graph/connect.py
xmlboiler/core/graph/minmax.py
xmlboiler/core/graph/path.py
xmlboiler/core/graph/relation.py
xmlboiler/core/interpreters/__init__.py
xmlboiler/core/interpreters/parse.py
xmlboiler/core/interpreters/parse_impl.py
xml_boiler-0.9.15.dist-info/COPYING
xml_boiler-0.9.15.dist-info/METADATA
xml_boiler-0.9.15.dist-info/WHEEL
xml_boiler-0.9.15.dist-info/top_level.txt
xml_boiler-0.9.15.dist-info/RECORD
