Metadata-Version: 2.1
Name: xml-boiler
Version: 0.9.15
Summary: Automatically transform between XML namespaces
Home-page: https://github.com/vporton/xml-boiler
Author: Victor Porton
Author-email: porton@narod.ru
License: AGPLv3
Keywords: XML,XML namespaces,file format conversion
Platform: UNKNOWN
Classifier: Development Status :: 3 - Alpha
Classifier: Environment :: Console
Classifier: Intended Audience :: Developers
Classifier: Intended Audience :: Information Technology
Classifier: License :: OSI Approved :: GNU Affero General Public License v3 or later (AGPLv3+)
Classifier: Operating System :: OS Independent
Classifier: Programming Language :: Python :: 3.7
Classifier: Topic :: Other/Nonlisted Topic
Classifier: Topic :: Text Processing :: Filters
Classifier: Topic :: Text Processing :: Markup :: XML
Requires-Dist: coverage
Requires-Dist: deb-pkg-tools
Requires-Dist: defusedxml
Requires-Dist: dependency-injector
Requires-Dist: distro
Requires-Dist: executor
Requires-Dist: networkx
Requires-Dist: ordered-set
Requires-Dist: rdflib
